    {
        "ctpvCd": null,
        "sggCd": "000",
        "ctpvNm": null,
        "sggNm": "본청"
    },
    {
        "ctpvCd": null,
        "sggCd": "150",
        "ctpvNm": null,
        "sggNm": "강릉시"
    },
    {
        "ctpvCd": null,
        "sggCd": "820",
        "ctpvNm": null,
        "sggNm": "고성군"
    },
    {
        "ctpvCd": null,
        "sggCd": "170",
        "ctpvNm": null,
        "sggNm": "동해시"
    },
    {
        "ctpvCd": null,
        "sggCd": "230",
        "ctpvNm": null,
        "sggNm": "삼척시"
    },
    {
        "ctpvCd": null,
        "sggCd": "210",
        "ctpvNm": null,
        "sggNm": "속초시"
    },
    {
        "ctpvCd": null,
        "sggCd": "800",
        "ctpvNm": null,
        "sggNm": "양구군"
    },
    {
        "ctpvCd": null,
        "sggCd": "830",
        "ctpvNm": null,
        "sggNm": "양양군"
    },
    {
        "ctpvCd": null,
        "sggCd": "750",
        "ctpvNm": null,
        "sggNm": "영월군"
    },
    {
        "ctpvCd": null,
        "sggCd": "130",
        "ctpvNm": null,
        "sggNm": "원주시"
    },
    {
        "ctpvCd": null,
        "sggCd": "810",
        "ctpvNm": null,
        "sggNm": "인제군"
    },
    {
        "ctpvCd": null,
        "sggCd": "770",
        "ctpvNm": null,
        "sggNm": "정선군"
    },
    {
        "ctpvCd": null,
        "sggCd": "780",
        "ctpvNm": null,
        "sggNm": "철원군"
    },
    {
        "ctpvCd": null,
        "sggCd": "110",
        "ctpvNm": null,
        "sggNm": "춘천시"
    },
    {
        "ctpvCd": null,
        "sggCd": "190",
        "ctpvNm": null,
        "sggNm": "태백시"
    },
    {
        "ctpvCd": null,
        "sggCd": "760",
        "ctpvNm": null,
        "sggNm": "평창군"
    },
    {
        "ctpvCd": null,
        "sggCd": "720",
        "ctpvNm": null,
        "sggNm": "홍천군"
    },
    {
        "ctpvCd": null,
        "sggCd": "790",
        "ctpvNm": null,
        "sggNm": "화천군"
    },
    {
        "ctpvCd": null,
        "sggCd": "730",
        "ctpvNm": null,
        "sggNm": "횡성군"
    }