    {
        "ctpvCd": null,
        "sggCd": "000",
        "ctpvNm": null,
        "sggNm": "본청"
    },
    {
        "ctpvCd": null,
        "sggCd": "250",
        "ctpvNm": null,
        "sggNm": "계룡시"
    },
    {
        "ctpvCd": null,
        "sggCd": "150",
        "ctpvNm": null,
        "sggNm": "공주시"
    },
    {
        "ctpvCd": null,
        "sggCd": "710",
        "ctpvNm": null,
        "sggNm": "금산군"
    },
    {
        "ctpvCd": null,
        "sggCd": "230",
        "ctpvNm": null,
        "sggNm": "논산시"
    },
    {
        "ctpvCd": null,
        "sggCd": "270",
        "ctpvNm": null,
        "sggNm": "당진시"
    },
    {
        "ctpvCd": null,
        "sggCd": "180",
        "ctpvNm": null,
        "sggNm": "보령시"
    },
    {
        "ctpvCd": null,
        "sggCd": "760",
        "ctpvNm": null,
        "sggNm": "부여군"
    },
    {
        "ctpvCd": null,
        "sggCd": "210",
        "ctpvNm": null,
        "sggNm": "서산시"
    },
    {
        "ctpvCd": null,
        "sggCd": "770",
        "ctpvNm": null,
        "sggNm": "서천군"
    },
    {
        "ctpvCd": null,
        "sggCd": "200",
        "ctpvNm": null,
        "sggNm": "아산시"
    },
    {
        "ctpvCd": null,
        "sggCd": "810",
        "ctpvNm": null,
        "sggNm": "예산군"
    },
    {
        "ctpvCd": null,
        "sggCd": "130",
        "ctpvNm": null,
        "sggNm": "천안시"
    },
    {
        "ctpvCd": null,
        "sggCd": "790",
        "ctpvNm": null,
        "sggNm": "청양군"
    },
    {
        "ctpvCd": null,
        "sggCd": "825",
        "ctpvNm": null,
        "sggNm": "태안군"
    },
    {
        "ctpvCd": null,
        "sggCd": "800",
        "ctpvNm": null,
        "sggNm": "홍성군"
    }